qsc/__init__.py
qsc/_version.py
qsc/cli.py
qsc/grpcProxy.py
qsc/main.py
qsc/measure.py
qsc/core/AddressState.py
qsc/core/Block.py
qsc/core/BlockHeader.py
qsc/core/BlockMetadata.py
qsc/core/ChainManager.py
qsc/core/DifficultyTracker.py
qsc/core/ESyncState.py
qsc/core/GenesisBlock.py
qsc/core/Indexer.py
qsc/core/LastTransactions.py
qsc/core/Message.py
qsc/core/MessageRequest.py
qsc/core/Miner.py
qsc/core/MultiSigAddressState.py
qsc/core/OptimizedAddressState.py
qsc/core/OutgoingMessage.py
qsc/core/PaginatedBitfield.py
qsc/core/PaginatedData.py
qsc/core/PoWValidator.py
qsc/core/ProposalRecord.py
qsc/core/Singleton.py
qsc/core/State.py
qsc/core/StateContainer.py
qsc/core/StateMigration.py
qsc/core/TokenList.py
qsc/core/TokenMetadata.py
qsc/core/TransactionInfo.py
qsc/core/TransactionMetadata.py
qsc/core/TransactionPool.py
qsc/core/VoteStats.py
qsc/core/Wallet.py
qsc/core/__init__.py
qsc/core/config.py
qsc/core/formulas.py
qsc/core/messagereceipt.py
qsc/core/node.py
qsc/core/qrlnode.py
qsc/core/miners/__init__.py
qsc/core/miners/qrandomx/QRXMiner.py
qsc/core/miners/qrandomx/QRXPoWValidator.py
qsc/core/miners/qrandomx/__init__.py
qsc/core/miners/qryptonight7/CNv1Miner.py
qsc/core/miners/qryptonight7/CNv1PoWValidator.py
qsc/core/miners/qryptonight7/__init__.py
qsc/core/misc/DependencyChecker.py
qsc/core/misc/__init__.py
qsc/core/misc/db.py
qsc/core/misc/expiring_set.py
qsc/core/misc/helper.py
qsc/core/misc/logger.py
qsc/core/misc/logger_twisted.py
qsc/core/misc/ntp.py
qsc/core/misc/set_logger.py
qsc/core/notification/Observable.py
qsc/core/notification/ObservableEvent.py
qsc/core/notification/__init__.py
qsc/core/p2p/IPMetadata.py
qsc/core/p2p/__init__.py
qsc/core/p2p/p2pChainManager.py
qsc/core/p2p/p2pObservable.py
qsc/core/p2p/p2pObserver.py
qsc/core/p2p/p2pPeerManager.py
qsc/core/p2p/p2pTxManagement.py
qsc/core/p2p/p2pfactory.py
qsc/core/p2p/p2pprotocol.py
qsc/core/processors/TxnProcessor.py
qsc/core/processors/__init__.py
qsc/core/txs/CoinBase.py
qsc_node_qscf-1.0.0.dist-info/LICENSE.txt
qsc_node_qscf-1.0.0.dist-info/METADATA
qsc_node_qscf-1.0.0.dist-info/WHEEL
qsc_node_qscf-1.0.0.dist-info/top_level.txt
qsc_node_qscf-1.0.0.dist-info/RECORD
